vsmodel/CorotModel.py
vsmodel/Dipole.py
vsmodel/MCModel.py
vsmodel/ModelCart.py
vsmodel/ModelE.py
vsmodel/ModelPol.py
vsmodel/PlotModelEq.py
vsmodel/PlotPlanet.py
vsmodel/PlotVectorEq.py
vsmodel/Potential.py
vsmodel/PotentialCart.py
vsmodel/PotentialPol.py
vsmodel/SAPSModel.py
vsmodel/SWModel.py
vsmodel/VExB.py
vsmodel/VExBModel.py
vsmodel/__init__.py
vsmodel-2.0.0.dist-info/LICENSE
vsmodel-2.0.0.dist-info/METADATA
vsmodel-2.0.0.dist-info/WHEEL
vsmodel-2.0.0.dist-info/top_level.txt
vsmodel-2.0.0.dist-info/RECORD
