Metadata-Version: 2.1
Name: vsmodel
Version: 2.0.0
Summary: A simple implementation of the Volland-Stern electric field model.
Home-page: https://github.com/mattkjames7/vsmodel
Author: Matthew Knight James
Author-email: mattkjames7@gmail.com
License: UNKNOWN
Platform: UNKNOWN
Classifier: Programming Language :: Python :: 3
Classifier: License :: OSI Approved :: MIT License
Requires-Dist: numpy
Requires-Dist: matplotlib
